jax_rocm60_plugin/_blas.so
jax_rocm60_plugin/_hybrid.so
jax_rocm60_plugin/_linalg.so
jax_rocm60_plugin/_prng.so
jax_rocm60_plugin/_rnn.so
jax_rocm60_plugin/_solver.so
jax_rocm60_plugin/_sparse.so
jax_rocm60_plugin/_triton.so
jax_rocm60_plugin/rocm_plugin_extension.so
jax_rocm60_plugin/version.py
jax_rocm60_plugin-0.5.0.dist-info/METADATA
jax_rocm60_plugin-0.5.0.dist-info/WHEEL
jax_rocm60_plugin-0.5.0.dist-info/top_level.txt
jax_rocm60_plugin-0.5.0.dist-info/RECORD
