Metadata-Version: 2.1
Name: jax-rocm60-plugin
Version: 0.5.0
Summary: JAX Plugin for AMD GPUs (ROCm:unknown)
Home-page: https://github.com/jax-ml/jax
Author: Ruturaj4
Author-email: Ruturaj.Vaidya@amd.com
License: Apache-2.0
Classifier: Development Status :: 3 - Alpha
Classifier: Programming Language :: Python :: 3.9
Classifier: Programming Language :: Python :: 3.10
Classifier: Programming Language :: Python :: 3.11
Classifier: Programming Language :: Python :: 3.12
Requires-Python: >=3.9
Requires-Dist: jax-rocm60-pjrt ==0.5.0
